{"g2048_layout":{"__class":"DisplayLayout","__childs":[{"__module":"AUIPlugin","__extends":"aui_bg"},{"text":"2048","__extends":"usual_label","y_value":8,"x_value":9,"__module":"AUIPlugin"},{"__extends":"common_train_layout","y_value":25,"__link":"_train","__target_class":["ADeeplearning","G2048TrainLayout"],"__module":"ADeeplearning","x_value":26},{"__class":"DisplayLayout","__childs":[{"__class":"DisplayLayout","__childs":[{"text":"0","__extends":"usual_label","y_value":5,"__link":"_2048_0_0","__module":"AUIPlugin"},{"text":"0","__extends":"usual_label","y_value":5,"__link":"_2048_0_1","x_value":35,"__module":"AUIPlugin"},{"text":"?","__extends":"usual_label","y_value":5,"__link":"_2048_0_3","x_value":102,"__module":"AUIPlugin"},{"text":"->","__extends":"usual_label","y_value":5,"__link":"_2048_0_2","x_value":73,"__module":"AUIPlugin"}],"width_type":4,"height_value":29},{"__class":"DisplayLayout","__childs":[{"text":"0","__extends":"usual_label","y_value":5,"__link":"_2048_1_0","__module":"AUIPlugin"},{"text":"1","__extends":"usual_label","y_value":5,"__link":"_2048_1_1","x_value":35,"__module":"AUIPlugin"},{"text":"?","__extends":"usual_label","y_value":5,"__link":"_2048_1_3","x_value":102,"__module":"AUIPlugin"},{"text":"->","__extends":"usual_label","y_value":5,"__link":"_2048_1_2","x_value":73,"__module":"AUIPlugin"}],"y_value":22,"height_value":29,"width_type":4},{"__class":"DisplayLayout","__childs":[{"text":"1","__extends":"usual_label","y_value":5,"__link":"_2048_2_0","__module":"AUIPlugin"},{"text":"0","__extends":"usual_label","y_value":5,"__link":"_2048_2_1","x_value":35,"__module":"AUIPlugin"},{"text":"?","__extends":"usual_label","y_value":5,"__link":"_2048_2_3","x_value":102,"__module":"AUIPlugin"},{"text":"->","__extends":"usual_label","y_value":5,"__link":"_2048_2_2","x_value":73,"__module":"AUIPlugin"}],"y_value":46,"height_value":29,"width_type":4},{"__class":"DisplayLayout","__childs":[{"text":"1","__extends":"usual_label","y_value":5,"__link":"_2048_3_0","__module":"AUIPlugin"},{"text":"1","__extends":"usual_label","y_value":5,"__link":"_2048_3_1","x_value":35,"__module":"AUIPlugin"},{"text":"?","__extends":"usual_label","y_value":5,"__link":"_2048_3_3","x_value":102,"__module":"AUIPlugin"},{"text":"->","__extends":"usual_label","y_value":5,"__link":"_2048_3_2","x_value":73,"__module":"AUIPlugin"}],"y_value":71,"height_value":29,"width_type":4},{"y_type":4,"__extends":"usual_button","y_value":81,"x_type":3,"__event":[{"func":"HandleCalcLeftClick","type":"ALittle.UIClickEvent"}],"x_value":-48,"__module":"AUIPlugin","text":"左移"},{"y_type":4,"__extends":"usual_button","y_value":81,"x_type":3,"text":"右移","x_value":16,"__module":"AUIPlugin","__event":[{"func":"HandleCalcRightClick","type":"ALittle.UIClickEvent"}]},{"y_type":4,"__extends":"usual_button","y_value":50,"x_type":3,"__event":[{"func":"HandleCalcDownClick","type":"ALittle.UIClickEvent"}],"x_value":16,"__module":"AUIPlugin","text":"下移"},{"y_type":4,"__extends":"usual_button","y_value":50,"x_type":3,"text":"上移","x_value":-48,"__module":"AUIPlugin","__event":[{"func":"HandleCalcUpClick","type":"ALittle.UIClickEvent"}]},{"y_type":4,"x_type":3,"text":"重新开始","__extends":"usual_button","y_value":15,"__event":[{"func":"HandleRestartClick","type":"ALittle.UIClickEvent"}],"x_value":-42,"__module":"AUIPlugin","width_value":63},{"y_type":4,"x_type":3,"text":"AI移动","__extends":"usual_button","y_value":15,"__event":[{"func":"HandleCalcAIClick","type":"ALittle.UIClickEvent"}],"x_value":22,"__module":"AUIPlugin","width_value":51}],"y_value":24,"x_type":4,"height_value":205,"x_value":37,"width_value":152}],"height_value":257,"__target_class":["ADeeplearning","G2048Layout"],"width_value":470}}